sentry_dingtalk_notify/__init__.py
sentry_dingtalk_notify/__version__.py
sentry_dingtalk_notify/plugin.py
sentry_dingtalk_notify-2.1.0.dist-info/licenses/LICENSE
sentry_dingtalk_notify-2.1.0.dist-info/METADATA
sentry_dingtalk_notify-2.1.0.dist-info/WHEEL
sentry_dingtalk_notify-2.1.0.dist-info/entry_points.txt
sentry_dingtalk_notify-2.1.0.dist-info/top_level.txt
sentry_dingtalk_notify-2.1.0.dist-info/RECORD
