Metadata-Version: 2.4
Name: sentry-dingtalk-notify
Version: 2.1.0
Summary: A sentry extension integrates DingTalk robot webhook
Home-page: https://github.com/lanxuexing/sentry-dingtalk-notify
Author: lanxuexing
Author-email: lanxuexing313wsr@163.com
License: MIT
Classifier: License :: OSI Approved :: MIT License
Classifier: Intended Audience :: Developers
Classifier: Intended Audience :: System Administrators
Classifier: Operating System :: OS Independent
Classifier: Topic :: Software Development
Classifier: Programming Language :: Python :: 3
Classifier: Programming Language :: Python :: 3.6
Classifier: Programming Language :: Python :: 3.7
Classifier: Programming Language :: Python :: 3.8
Classifier: Programming Language :: Python :: 3.9
Classifier: Programming Language :: Python :: 3.10
Classifier: Programming Language :: Python :: Implementation :: CPython
Classifier: Framework :: Django
License-File: LICENSE
Requires-Dist: sentry>=9.0.0
Requires-Dist: requests
Dynamic: author
Dynamic: author-email
Dynamic: classifier
Dynamic: description
Dynamic: description-content-type
Dynamic: home-page
Dynamic: license
Dynamic: license-file
Dynamic: requires-dist
Dynamic: summary
